{
  "Video_with_Faces_Ready": {
    "config": {
      "video_codec": "h264",
      "resolution": "1080",
      "target_fps": "15",
      "audio_enabled": "no",
      "audio_codec": "aac",
      "hardware_accel": "no",
      "duration_hours": "6",
      "encoder_details": {
        "name": "libx264",
        "type": "software"
      },
      "stream_type": "file",
      "source_url": null,
      "video_file": "Video_with_Faces_Ready.mp4",
      "file_source_type": "folder",
      "video_file_path": "/Users/tom.broyer/dev/OnStream_Project/StreamAlchemy/python_interface/browseable_videos/Video_with_Faces_Ready.mp4"
    },
    "saved_at": 1759910342.911654,
    "status": "active"
  }
}